text-abbtreviate/__init__.py
text-abbtreviate/text_abbtreviate.py
text_abbtreviate/__init__.py
text_abbtreviate/abbreviate.py
text_abbreviator-1.0.0.dist-info/METADATA
text_abbreviator-1.0.0.dist-info/WHEEL
text_abbreviator-1.0.0.dist-info/top_level.txt
text_abbreviator-1.0.0.dist-info/RECORD
