Metadata-Version: 2.1
Name: text-abbreviator
Version: 1.0.0
Summary: Text String processing library
Home-page: https://github.com/loeaf/text-abbreviate
Author: loeaf
Author-email: break8524@gamil.com
